[{"id":"all-bran-(uk/aus)","name":"All-bran (UK/Aus)","gi":"30"},{"id":"all-bran-(us)","name":"All-bran (US)","gi":"50"},{"id":"oat-bran","name":"Oat bran","gi":"50"},{"id":"rolled-oats","name":"Rolled Oats","gi":"51"},{"id":"special-k-(uk/aus)","name":"Special K (UK/Aus)","gi":"54"},{"id":"natural-muesli","name":"Natural Muesli","gi":"40"},{"id":"porridge","name":"Porridge","gi":"58"},{"id":"bran-buds","name":"Bran Buds","gi":"58"},{"id":"mini-wheats","name":"Mini Wheats","gi":"58"},{"id":"nutrigrain","name":"Nutrigrain","gi":"66"},{"id":"shredded-wheat","name":"Shredded Wheat","gi":"67"},{"id":"porridge-oats","name":"Porridge Oats","gi":"63"},{"id":"special-k-(us)","name":"Special K (US)","gi":"69"},{"id":"cornflakes","name":"Cornflakes","gi":"80"},{"id":"sultana-bran","name":"Sultana Bran","gi":"73"},{"id":"branflakes","name":"Branflakes","gi":"74"},{"id":"coco-pops","name":"Coco Pops","gi":"77"},{"id":"puffed-wheat","name":"Puffed Wheat","gi":"80"},{"id":"oats-in-honey-bake","name":"Oats in Honey Bake","gi":"77"},{"id":"team","name":"Team","gi":"82"},{"id":"total","name":"Total","gi":"76"},{"id":"cheerios","name":"Cheerios","gi":"74"},{"id":"rice-krispies","name":"Rice Krispies","gi":"82"},{"id":"weetabix","name":"Weetabix","gi":"74"},{"id":"wheat-pasta-shapes","name":"Wheat Pasta Shapes","gi":"54 "},{"id":"new-potatoes","name":"New Potatoes","gi":" 54"},{"id":"meat-ravioli","name":"Meat Ravioli","gi":"39"},{"id":"spaghetti","name":"Spaghetti","gi":"32 "},{"id":"tortellini-(cheese)","name":"Tortellini (Cheese)","gi":"50"},{"id":"egg-fettuccini","name":"Egg Fettuccini","gi":"32"},{"id":"brown-rice","name":"Brown Rice","gi":"50 "},{"id":"buckwheat","name":"Buckwheat","gi":"51 "},{"id":"white-long-grain-rice","name":"White long grain rice","gi":"50 "},{"id":"pearled-barley","name":"Pearled Barley","gi":"22 "},{"id":"yam","name":"Yam","gi":"35 "},{"id":"sweet-potatoes","name":"Sweet Potatoes","gi":"48 "},{"id":"instant-noodles","name":"Instant Noodles","gi":"47"},{"id":"wheat-tortilla","name":"Wheat tortilla","gi":"30"},{"id":"basmati-rice","name":"Basmati Rice","gi":"58 "},{"id":"couscous","name":"Couscous","gi":"61 "},{"id":"cornmeal","name":"Cornmeal","gi":"68 "},{"id":"taco-shells","name":"Taco Shells","gi":"68 "},{"id":"gnocchi","name":"Gnocchi","gi":"68 "},{"id":"canned-potatoes","name":"Canned Potatoes","gi":"61 "},{"id":"chinese-(rice)-vermicelli","name":"Chinese (Rice) Vermicelli","gi":"58"},{"id":"baked-potatoes","name":"Baked Potatoes","gi":"60"},{"id":"wild-rice","name":"Wild Rice","gi":"57"},{"id":"instant-white-rice","name":"Instant White Rice","gi":"87 "},{"id":"glutinous-rice","name":"Glutinous Rice","gi":"86 "},{"id":"short-grain-white-rice","name":"Short Grain White Rice","gi":"83 "},{"id":"tapioca","name":"Tapioca","gi":"70 "},{"id":"fresh-mashed-potatoes","name":"Fresh Mashed Potatoes","gi":"73 "},{"id":"french-fries","name":"French Fries","gi":"75 "},{"id":"instant-mashed-potatoes","name":"Instant Mashed Potatoes","gi":"80 "},{"id":"soya-and-linseed","name":"Soya and Linseed","gi":"36"},{"id":"wholegrain-pumpernickel","name":"Wholegrain Pumpernickel","gi":"46 "},{"id":"heavy-mixed-grain","name":"Heavy Mixed Grain","gi":"45"},{"id":"whole-wheat","name":"Whole Wheat","gi":"49"},{"id":"sourdough-rye","name":"Sourdough Rye","gi":"48"},{"id":"sourdough-wheat","name":"Sourdough Wheat","gi":"54"},{"id":"croissant","name":"Croissant","gi":"67 "},{"id":"hamburger-bun","name":"Hamburger bun","gi":"61"},{"id":"pita,-white","name":"Pita, white","gi":"57"},{"id":"wholemeal-rye","name":"Wholemeal Rye","gi":"62"},{"id":"white","name":"White","gi":"71"},{"id":"bagel","name":"Bagel","gi":"72"},{"id":"french-baguette","name":"French Baguette","gi":"95"},{"id":"slim-fast-meal-replacement","name":"Slim-Fast meal replacement","gi":"27"},{"id":"snickers-bar-(high-fat)","name":"Snickers Bar (high fat)","gi":"41"},{"id":"nut-&-seed-muesli-bar","name":"Nut & Seed Muesli Bar","gi":"49"},{"id":"sponge-cake","name":"Sponge Cake","gi":"46 "},{"id":"nutella","name":"Nutella","gi":"33 "},{"id":"milk-chocolate","name":"Milk Chocolate","gi":"42 "},{"id":"hummus","name":"Hummus","gi":"6"},{"id":"peanuts","name":"Peanuts","gi":"13 "},{"id":"walnuts","name":"Walnuts","gi":"15"},{"id":"cashew-nuts","name":"Cashew Nuts","gi":"25 "},{"id":"nuts-and-raisins","name":"Nuts and Raisins","gi":"21"},{"id":"jam","name":"Jam","gi":"51"},{"id":"corn-chips","name":"Corn Chips","gi":"42"},{"id":"oatmeal-crackers","name":"Oatmeal Crackers","gi":"55"},{"id":"ryvita","name":"Ryvita","gi":"63 "},{"id":"digestives","name":"Digestives","gi":"59 "},{"id":"blueberry-muffin","name":"Blueberry muffin","gi":"59 "},{"id":"honey","name":"Honey","gi":"58 "},{"id":"pretzels","name":"Pretzels","gi":"83 "},{"id":"water-crackers","name":"Water Crackers","gi":"78 "},{"id":"rice-cakes","name":"Rice cakes","gi":"87 "},{"id":"puffed-crispbread","name":"Puffed Crispbread","gi":"81 "},{"id":"donuts","name":"Donuts","gi":"76 "},{"id":"scones","name":"Scones","gi":"92 "},{"id":"maple-flavoured-syrup","name":"Maple flavoured syrup","gi":"68 "},{"id":"kidney-beans-(canned)","name":"Kidney Beans (canned)","gi":"52"},{"id":"butter-beans","name":"Butter Beans","gi":"36 "},{"id":"chick-peas","name":"Chick Peas","gi":"42 "},{"id":"haricot/navy-beans","name":"Haricot/Navy Beans","gi":"31 "},{"id":"lentils,-red","name":"Lentils, Red","gi":"21 "},{"id":"lentils,-green","name":"Lentils, Green","gi":"30 "},{"id":"pinto-beans","name":"Pinto Beans","gi":"45 "},{"id":"blackeyed-beans","name":"Blackeyed Beans","gi":"50 "},{"id":"yellow-split-peas","name":"Yellow Split Peas","gi":"32 "},{"id":"beans-in-tomato-sauce","name":"Beans in Tomato Sauce","gi":"56 "},{"id":"frozen-green-peas","name":"Frozen Green Peas","gi":"39"},{"id":"frozen-sweet-corn","name":"Frozen Sweet Corn","gi":"47"},{"id":"raw-carrots","name":"Raw Carrots","gi":"16"},{"id":"boiled-carrots","name":"Boiled Carrots","gi":"41"},{"id":"eggplant/aubergine","name":"Eggplant/Aubergine","gi":"15"},{"id":"broccoli","name":"Broccoli","gi":"10"},{"id":"cauliflower","name":"Cauliflower","gi":"15"},{"id":"cabbage","name":"Cabbage","gi":"10"},{"id":"mushrooms","name":"Mushrooms","gi":"10"},{"id":"tomatoes","name":"Tomatoes","gi":"15"},{"id":"chillies","name":"Chillies","gi":"10"},{"id":"lettuce","name":"Lettuce","gi":"10"},{"id":"green-beans","name":"Green Beans","gi":"15"},{"id":"red-peppers","name":"Red Peppers","gi":"10"},{"id":"onions","name":"Onions","gi":"10"},{"id":"beetroot","name":"Beetroot","gi":"64"},{"id":"pumkin","name":"Pumkin","gi":"75"},{"id":"parsnips","name":"Parsnips","gi":"97"},{"id":"cherries","name":"Cherries","gi":"22 "},{"id":"plums","name":"Plums","gi":"24 "},{"id":"grapefruit","name":"Grapefruit","gi":"25 "},{"id":"peaches","name":"Peaches","gi":"28 "},{"id":"peach,-canned-in-natural-juice","name":"Peach, canned in natural juice","gi":"30"},{"id":"apples","name":"Apples","gi":"34"},{"id":"pears","name":"Pears","gi":"41"},{"id":"dried-apricots","name":"Dried Apricots","gi":"32"},{"id":"grapes","name":"Grapes","gi":"43"},{"id":"coconut","name":"Coconut","gi":"45"},{"id":"coconut-milk","name":"Coconut Milk","gi":"41"},{"id":"kiwi-fruit","name":"Kiwi Fruit","gi":"47"},{"id":"oranges","name":"Oranges","gi":"40"},{"id":"strawberries","name":"Strawberries","gi":"40"},{"id":"prunes","name":"Prunes","gi":"29"},{"id":"mango","name":"Mango","gi":"60 "},{"id":"sultanas","name":"Sultanas","gi":"56 "},{"id":"bananas","name":"Bananas","gi":"58 "},{"id":"raisins","name":"Raisins","gi":"64 "},{"id":"papaya","name":"Papaya","gi":"60 "},{"id":"figs","name":"Figs","gi":"61"},{"id":"pineapple","name":"Pineapple","gi":"66"},{"id":"watermelon","name":"Watermelon","gi":"80 "},{"id":"dates","name":"Dates","gi":"103 "},{"id":"whole-milk","name":"Whole milk","gi":"31 "},{"id":"skimmed-milk","name":"Skimmed milk","gi":"32"},{"id":"chocolate-milk","name":"Chocolate milk","gi":"42"},{"id":"sweetened-yoghurt","name":"Sweetened yoghurt","gi":"33"},{"id":"artificially-sweetened-yoghurt","name":"Artificially Sweetened Yoghurt","gi":"23"},{"id":"custard","name":"Custard","gi":"35"},{"id":"soy-milk","name":"Soy Milk","gi":"44"},{"id":"icecream","name":"Icecream","gi":"62"}]